ragutils/__init__.py
ragutils/document_loaders.py
ragutils/embedding_providers.py
ragutils/text_splitters.py
ragutils/vector_databases.py
ragutils-0.1.0.dist-info/LICENSE
ragutils-0.1.0.dist-info/METADATA
ragutils-0.1.0.dist-info/WHEEL
ragutils-0.1.0.dist-info/top_level.txt
ragutils-0.1.0.dist-info/RECORD
