Metadata-Version: 2.1
Name: ragutils
Version: 0.1.0
Summary: A package that abstracts most of the utilities used in RAG applications
Author-email: Koleshjr <koleshjr@gmail.com>
License: Apache License
Project-URL: Homepage, https://github.com/koleshjr/ragutils
Keywords: document loaders,embedding providers,text splitters,vector databases
Classifier: License :: OSI Approved :: Apache Software License
Classifier: Programming Language :: Python :: 3
Requires-Python: >=3.9
License-File: LICENSE
Requires-Dist: pinecone-client >=3.2.2
Requires-Dist: pypdf >=4.1.0
Requires-Dist: unstructured >=0.13.2
Requires-Dist: langchain-community >=0.0.31
Requires-Dist: langchain >=0.1.14
Requires-Dist: langchain-openai >=0.1.1
Requires-Dist: langchain-google-genai >=1.0.1
Requires-Dist: langchain-pinecone >=0.1.0
Requires-Dist: google.generativeai >=0.4.1
Requires-Dist: python-dotenv >=1.0.1
Requires-Dist: docx2txt >=0.8
Requires-Dist: python-docx >=1.1.0
Requires-Dist: markdown >=3.6
Requires-Dist: beautifulsoup4 >=4.12.3
Requires-Dist: langchain-experimental >=0.0.57
Requires-Dist: nltk >=3.8.1
Requires-Dist: fastembed >=0.2.6
Requires-Dist: cohere >=5.1.4
Requires-Dist: langchain-cohere >=0.1.3
Requires-Dist: qdrant-client >=1.9.0
Requires-Dist: pymilvus >=2.4.0
Requires-Dist: docarray >=0.40.0
Requires-Dist: chromadb >=0.4.24
Requires-Dist: faiss-cpu >=1.8.0
Provides-Extra: dev
Requires-Dist: black ; extra == 'dev'
Requires-Dist: bumpver ; extra == 'dev'
Requires-Dist: isort ; extra == 'dev'
Requires-Dist: pip-tools ; extra == 'dev'
Requires-Dist: pytest ; extra == 'dev'
